{"assets":{"271E6B242872962F423F8023680B6992":{"type":"texture","index":0,"url":{"native":"assets\/A843A5DD-E902-47D9-BD4A-4270D282A93D.pdf"},"width":1920,"height":1080},"1CFDC2A82EB2CA0D4C2841C25C1D2E01":{"type":"texture","index":1,"url":{"native":"assets\/A843A5DD-E902-47D9-BD4A-4270D282A93D.pdf"},"width":1920,"height":1080}},"events":[{"effects":[{"beginTime":0,"baseLayer":{"animations":[],"initialState":{"affineTransform":[1,0,0,1,0,0],"masksToBounds":false,"rotation":0,"scale":1,"position":{"pointX":960,"pointY":540},"width":1920,"sublayerTransform":[1,0,0,0,0,1,0,0,0,0,1,0,0,0,0,1],"contentsRect":{"y":0,"x":0,"width":1,"height":1},"opacity":1,"edgeAntialiasingMask":251658240,"height":1080,"hidden":false,"anchorPoint":{"pointX":0.5,"pointY":0.5}},"objectID":"0","layers":[{"animations":[],"initialState":{"affineTransform":[1,0,0,1,0,0],"masksToBounds":false,"rotation":0,"scale":1,"position":{"pointX":960,"pointY":540},"width":1920,"sublayerTransform":[1,0,0,0,0,1,0,0,0,0,1,-0.00035007912466775983,0,0,0,1],"contentsRect":{"y":0,"x":0,"width":1,"height":1},"opacity":1,"edgeAntialiasingMask":251658240,"height":1080,"hidden":false,"anchorPoint":{"pointX":0.5,"pointY":0.5}},"layers":[{"animations":[],"layers":[],"texturedRectangle":{"isBackgroundTexture":false,"singleTextureOpacity":1,"textureType":0,"textBaseline":0,"textXHeight":0,"isVerticalText":false},"initialState":{"affineTransform":[1,0,0,1,0,0],"masksToBounds":false,"rotation":0,"scale":1,"position":{"pointX":960,"pointY":540},"width":1920,"sublayerTransform":[1,0,0,0,0,1,0,0,0,0,1,0,0,0,0,1],"contentsRect":{"y":0,"x":0,"width":1,"height":1},"opacity":1,"edgeAntialiasingMask":0,"height":1080,"hidden":false,"anchorPoint":{"pointX":0.5,"pointY":0.5}},"texture":"1CFDC2A82EB2CA0D4C2841C25C1D2E01"},{"animations":[{"additive":false,"timeOffset":0,"beginTime":0,"from":{"scalar":false},"repeatCount":0,"fillMode":"both","duration":0.01,"autoreverses":false,"property":"hidden","to":{"scalar":true},"removedOnCompletion":false}],"layers":[],"texturedRectangle":{"isBackgroundTexture":false,"singleTextureOpacity":1,"textureType":0,"textBaseline":0,"textXHeight":0,"isVerticalText":false},"initialState":{"affineTransform":[1,0,0,1,0,0],"masksToBounds":false,"rotation":0,"scale":1,"position":{"pointX":960,"pointY":540},"width":1920,"sublayerTransform":[1,0,0,0,0,1,0,0,0,0,1,0,0,0,0,1],"contentsRect":{"y":0,"x":0,"width":1,"height":1},"opacity":1,"edgeAntialiasingMask":0,"height":1080,"hidden":false,"anchorPoint":{"pointX":0.5,"pointY":0.5}},"texture":"271E6B242872962F423F8023680B6992"}]}]},"effects":[],"duration":0.01,"type":"transition","attributes":{"direction":0},"name":"none","objectID":"0"}],"automaticPlay":false,"hyperlinks":[{"url":"https:\/\/www.cream-paris.tv\/","targetRectangle":{"y":-5.6527961056599514,"x":1283.521667520441,"width":636.47833251953125,"height":1079.9999999999998}},{"url":"https:\/\/www.bonaparte.tv\/","targetRectangle":{"y":4.978869583283086e-08,"x":-1.6011199477361515e-07,"width":632.121337890625,"height":1080}},{"url":"https:\/\/www.humans.tv\/","targetRectangle":{"y":4.978869583283086e-08,"x":632.12133773495134,"width":650.40032958984375,"height":1079.9999999999998}}],"accessibility":[{"text":"HUMANS.png","targetRectangle":{"y":469.65603414773199,"x":733.71509877005383,"width":447.21282958984375,"height":129.38233947753912}},{"text":"CREAM.png","targetRectangle":{"y":463.17112772860838,"x":1370.3969591176847,"width":447.21282958984375,"height":153.65774536132807}},{"text":"Kerastase","targetRectangle":{"y":1028.5752260684967,"x":1018.1300048828125,"width":96.660000000000082,"height":24.41986083984375}},{"text":"￼","targetRectangle":{"y":1028.5751953125,"x":1858.6525832493207,"width":22.240000000000009,"height":24.41986083984375}},{"text":"pasted-image.pdf","targetRectangle":{"y":1032.987548828125,"x":35.152545928955078,"width":87.856109063454824,"height":16.125}},{"text":"Bonaparte.png","targetRectangle":{"y":426.15793609433166,"x":103.31255614845145,"width":397.33114624023438,"height":227.68412780761724}},{"text":"WWM Film","targetRectangle":{"y":1028.5752260684967,"x":1337.311279296875,"width":101.75999999999999,"height":24.41986083984375}}],"baseLayer":{"animations":[],"initialState":{"affineTransform":[1,0,0,1,0,0],"masksToBounds":false,"rotation":0,"scale":1,"position":{"pointX":960,"pointY":540},"width":1920,"sublayerTransform":[1,0,0,0,0,1,0,0,0,0,1,0,0,0,0,1],"contentsRect":{"y":0,"x":0,"width":1,"height":1},"opacity":1,"edgeAntialiasingMask":251658240,"height":1080,"hidden":false,"anchorPoint":{"pointX":0.5,"pointY":0.5}},"objectID":"0","layers":[{"animations":[],"initialState":{"affineTransform":[1,0,0,1,0,0],"masksToBounds":false,"rotation":0,"scale":1,"position":{"pointX":960,"pointY":540},"width":1920,"sublayerTransform":[1,0,0,0,0,1,0,0,0,0,1,-0.00035007912466775983,0,0,0,1],"contentsRect":{"y":0,"x":0,"width":1,"height":1},"opacity":1,"edgeAntialiasingMask":251658240,"height":1080,"hidden":false,"anchorPoint":{"pointX":0.5,"pointY":0.5}},"layers":[{"animations":[],"layers":[],"texturedRectangle":{"isBackgroundTexture":false,"singleTextureOpacity":1,"textureType":0,"textBaseline":0,"textXHeight":0,"isVerticalText":false},"initialState":{"affineTransform":[1,0,0,1,0,0],"masksToBounds":false,"rotation":0,"scale":1,"position":{"pointX":960,"pointY":540},"width":1920,"sublayerTransform":[1,0,0,0,0,1,0,0,0,0,1,0,0,0,0,1],"contentsRect":{"y":0,"x":0,"width":1,"height":1},"opacity":1,"edgeAntialiasingMask":0,"height":1080,"hidden":false,"anchorPoint":{"pointX":0.5,"pointY":0.5}},"texture":"271E6B242872962F423F8023680B6992"}]}]}}]}